{"efExports":[{"TypeRef":[{"runProperName":"Additive"},[{"runProperName":"Additive"}]]},{"ValueRef":{"Ident":"runAdditive"}},{"TypeInstanceRef":{"Ident":"eqAdditive"}},{"TypeInstanceRef":{"Ident":"ordAdditive"}},{"TypeInstanceRef":{"Ident":"functorAdditive"}},{"TypeInstanceRef":{"Ident":"applyAdditive"}},{"TypeInstanceRef":{"Ident":"applicativeAdditive"}},{"TypeInstanceRef":{"Ident":"bindAdditive"}},{"TypeInstanceRef":{"Ident":"monadAdditive"}},{"TypeInstanceRef":{"Ident":"extendAdditive"}},{"TypeInstanceRef":{"Ident":"comonadAdditive"}},{"TypeInstanceRef":{"Ident":"invariantAdditive"}},{"TypeInstanceRef":{"Ident":"showAdditive"}},{"TypeInstanceRef":{"Ident":"semigroupAdditive"}},{"TypeInstanceRef":{"Ident":"monoidAdditive"}}],"efImports":[{"eiImportedAs":null,"eiModule":[{"runProperName":"Prim"}],"eiImportType":{"Implicit":[]}},{"eiImportedAs":null,"eiModule":[{"runProperName":"Prelude"}],"eiImportType":{"Implicit":[]}},{"eiImportedAs":null,"eiModule":[{"runProperName":"Control"},{"runProperName":"Comonad"}],"eiImportType":{"Explicit":[{"PositionedDeclarationRef":[{"start":[5,25],"name":"/Users/paf31/Documents/Code/purescript/purescript/bower_components/purescript-monoid/src/Data/Monoid/Additive.purs","end":[5,32]},[],{"TypeClassRef":{"runProperName":"Comonad"}}]}]}},{"eiImportedAs":null,"eiModule":[{"runProperName":"Control"},{"runProperName":"Extend"}],"eiImportType":{"Explicit":[{"PositionedDeclarationRef":[{"start":[6,24],"name":"/Users/paf31/Documents/Code/purescript/purescript/bower_components/purescript-monoid/src/Data/Monoid/Additive.purs","end":[6,30]},[],{"TypeClassRef":{"runProperName":"Extend"}}]}]}},{"eiImportedAs":null,"eiModule":[{"runProperName":"Data"},{"runProperName":"Functor"},{"runProperName":"Invariant"}],"eiImportType":{"Explicit":[{"PositionedDeclarationRef":[{"start":[7,32],"name":"/Users/paf31/Documents/Code/purescript/purescript/bower_components/purescript-monoid/src/Data/Monoid/Additive.purs","end":[7,41]},[],{"TypeClassRef":{"runProperName":"Invariant"}}]},{"PositionedDeclarationRef":[{"start":[7,43],"name":"/Users/paf31/Documents/Code/purescript/purescript/bower_components/purescript-monoid/src/Data/Monoid/Additive.purs","end":[7,47]},[],{"ValueRef":{"Ident":"imap"}}]}]}},{"eiImportedAs":null,"eiModule":[{"runProperName":"Data"},{"runProperName":"Monoid"}],"eiImportType":{"Implicit":[]}}],"efVersion":"0.7.4.1","efDeclarations":[{"EDType":{"edTypeName":{"runProperName":"Additive"},"edTypeKind":{"tag":"FunKind","contents":[{"tag":"Star","contents":[]},{"tag":"Star","contents":[]}]},"edTypeDeclarationKind":{"DataType":[[["a",{"tag":"Star","contents":[]}]],[[{"runProperName":"Additive"},[{"tag":"TypeVar","contents":"a"}]]]]}}},{"EDDataConstructor":{"edDataCtorName":{"runProperName":"Additive"},"edDataCtorFields":[{"Ident":"value0"}],"edDataCtorType":{"tag":"ForAll","contents":["a",{"tag":"TypeApp","contents":[{"tag":"TypeApp","contents":[{"tag":"TypeConstructor","contents":"Prim.Function"},{"tag":"TypeVar","contents":"a"}]},{"tag":"TypeApp","contents":[{"tag":"TypeConstructor","contents":"Data.Monoid.Additive.Additive"},{"tag":"TypeVar","contents":"a"}]}]},null]},"edDataCtorTypeCtor":{"runProperName":"Additive"},"edDataCtorOrigin":"newtype"}},{"EDValue":{"edValueType":{"tag":"ForAll","contents":["a",{"tag":"TypeApp","contents":[{"tag":"TypeApp","contents":[{"tag":"TypeConstructor","contents":"Prim.Function"},{"tag":"TypeApp","contents":[{"tag":"TypeConstructor","contents":"Data.Monoid.Additive.Additive"},{"tag":"TypeVar","contents":"a"}]}]},{"tag":"TypeVar","contents":"a"}]},16]},"edValueName":{"Ident":"runAdditive"}}},{"EDInstance":{"edInstanceTypes":[{"tag":"TypeApp","contents":[{"tag":"TypeConstructor","contents":"Data.Monoid.Additive.Additive"},{"tag":"TypeVar","contents":"a"}]}],"edInstanceConstraints":[["Prelude.Eq",[{"tag":"TypeVar","contents":"a"}]]],"edInstanceName":{"Ident":"eqAdditive"},"edInstanceClassName":"Prelude.Eq"}},{"EDInstance":{"edInstanceTypes":[{"tag":"TypeApp","contents":[{"tag":"TypeConstructor","contents":"Data.Monoid.Additive.Additive"},{"tag":"TypeVar","contents":"a"}]}],"edInstanceConstraints":[["Prelude.Ord",[{"tag":"TypeVar","contents":"a"}]]],"edInstanceName":{"Ident":"ordAdditive"},"edInstanceClassName":"Prelude.Ord"}},{"EDInstance":{"edInstanceTypes":[{"tag":"TypeConstructor","contents":"Data.Monoid.Additive.Additive"}],"edInstanceConstraints":[],"edInstanceName":{"Ident":"functorAdditive"},"edInstanceClassName":"Prelude.Functor"}},{"EDInstance":{"edInstanceTypes":[{"tag":"TypeConstructor","contents":"Data.Monoid.Additive.Additive"}],"edInstanceConstraints":[],"edInstanceName":{"Ident":"applyAdditive"},"edInstanceClassName":"Prelude.Apply"}},{"EDInstance":{"edInstanceTypes":[{"tag":"TypeConstructor","contents":"Data.Monoid.Additive.Additive"}],"edInstanceConstraints":[],"edInstanceName":{"Ident":"applicativeAdditive"},"edInstanceClassName":"Prelude.Applicative"}},{"EDInstance":{"edInstanceTypes":[{"tag":"TypeConstructor","contents":"Data.Monoid.Additive.Additive"}],"edInstanceConstraints":[],"edInstanceName":{"Ident":"bindAdditive"},"edInstanceClassName":"Prelude.Bind"}},{"EDInstance":{"edInstanceTypes":[{"tag":"TypeConstructor","contents":"Data.Monoid.Additive.Additive"}],"edInstanceConstraints":[],"edInstanceName":{"Ident":"monadAdditive"},"edInstanceClassName":"Prelude.Monad"}},{"EDInstance":{"edInstanceTypes":[{"tag":"TypeConstructor","contents":"Data.Monoid.Additive.Additive"}],"edInstanceConstraints":[],"edInstanceName":{"Ident":"extendAdditive"},"edInstanceClassName":"Control.Extend.Extend"}},{"EDInstance":{"edInstanceTypes":[{"tag":"TypeConstructor","contents":"Data.Monoid.Additive.Additive"}],"edInstanceConstraints":[],"edInstanceName":{"Ident":"comonadAdditive"},"edInstanceClassName":"Control.Comonad.Comonad"}},{"EDInstance":{"edInstanceTypes":[{"tag":"TypeConstructor","contents":"Data.Monoid.Additive.Additive"}],"edInstanceConstraints":[],"edInstanceName":{"Ident":"invariantAdditive"},"edInstanceClassName":"Data.Functor.Invariant.Invariant"}},{"EDInstance":{"edInstanceTypes":[{"tag":"TypeApp","contents":[{"tag":"TypeConstructor","contents":"Data.Monoid.Additive.Additive"},{"tag":"TypeVar","contents":"a"}]}],"edInstanceConstraints":[["Prelude.Show",[{"tag":"TypeVar","contents":"a"}]]],"edInstanceName":{"Ident":"showAdditive"},"edInstanceClassName":"Prelude.Show"}},{"EDInstance":{"edInstanceTypes":[{"tag":"TypeApp","contents":[{"tag":"TypeConstructor","contents":"Data.Monoid.Additive.Additive"},{"tag":"TypeVar","contents":"a"}]}],"edInstanceConstraints":[["Prelude.Semiring",[{"tag":"TypeVar","contents":"a"}]]],"edInstanceName":{"Ident":"semigroupAdditive"},"edInstanceClassName":"Prelude.Semigroup"}},{"EDInstance":{"edInstanceTypes":[{"tag":"TypeApp","contents":[{"tag":"TypeConstructor","contents":"Data.Monoid.Additive.Additive"},{"tag":"TypeVar","contents":"a"}]}],"edInstanceConstraints":[["Prelude.Semiring",[{"tag":"TypeVar","contents":"a"}]]],"edInstanceName":{"Ident":"monoidAdditive"},"edInstanceClassName":"Data.Monoid.Monoid"}}],"efFixities":[],"efModuleName":[{"runProperName":"Data"},{"runProperName":"Monoid"},{"runProperName":"Additive"}]}