{"efExports":[{"ValueRef":{"Op":"$>"}},{"ValueRef":{"Op":"<$"}}],"efImports":[{"eiImportedAs":null,"eiModule":[{"runProperName":"Prim"}],"eiImportType":{"Implicit":[]}},{"eiImportedAs":null,"eiModule":[{"runProperName":"Prelude"}],"eiImportType":{"Implicit":[]}}],"efVersion":"0.7.4.1","efDeclarations":[{"EDValue":{"edValueType":{"tag":"ForAll","contents":["b",{"tag":"ForAll","contents":["a",{"tag":"ForAll","contents":["f",{"tag":"ConstrainedType","contents":[[["Prelude.Functor",[{"tag":"TypeVar","contents":"f"}]]],{"tag":"TypeApp","contents":[{"tag":"TypeApp","contents":[{"tag":"TypeConstructor","contents":"Prim.Function"},{"tag":"TypeApp","contents":[{"tag":"TypeVar","contents":"f"},{"tag":"TypeVar","contents":"a"}]}]},{"tag":"TypeApp","contents":[{"tag":"TypeApp","contents":[{"tag":"TypeConstructor","contents":"Prim.Function"},{"tag":"TypeVar","contents":"b"}]},{"tag":"TypeApp","contents":[{"tag":"TypeVar","contents":"f"},{"tag":"TypeVar","contents":"b"}]}]}]}]},14]},15]},16]},"edValueName":{"Op":"$>"}}},{"EDValue":{"edValueType":{"tag":"ForAll","contents":["b",{"tag":"ForAll","contents":["a",{"tag":"ForAll","contents":["f",{"tag":"ConstrainedType","contents":[[["Prelude.Functor",[{"tag":"TypeVar","contents":"f"}]]],{"tag":"TypeApp","contents":[{"tag":"TypeApp","contents":[{"tag":"TypeConstructor","contents":"Prim.Function"},{"tag":"TypeVar","contents":"a"}]},{"tag":"TypeApp","contents":[{"tag":"TypeApp","contents":[{"tag":"TypeConstructor","contents":"Prim.Function"},{"tag":"TypeApp","contents":[{"tag":"TypeVar","contents":"f"},{"tag":"TypeVar","contents":"b"}]}]},{"tag":"TypeApp","contents":[{"tag":"TypeVar","contents":"f"},{"tag":"TypeVar","contents":"a"}]}]}]}]},0]},1]},2]},"edValueName":{"Op":"<$"}}}],"efFixities":[{"efOperator":"<$","efAssociativity":"infixl","efPrecedence":4},{"efOperator":"$>","efAssociativity":"infixl","efPrecedence":4}],"efModuleName":[{"runProperName":"Data"},{"runProperName":"Functor"}]}